devrouw/__init__.py
devrouw/analysis.py
devrouw/visualization.py
tests/__init__.py
tests/test_analysis.py
tests/test_visualization.py
devrouw-0.1.1.dist-info/LICENSE
devrouw-0.1.1.dist-info/METADATA
devrouw-0.1.1.dist-info/WHEEL
devrouw-0.1.1.dist-info/top_level.txt
devrouw-0.1.1.dist-info/RECORD
