Metadata-Version: 2.1
Name: devrouw
Version: 0.1.1
Summary: A Python library for data analysis and visualization
Home-page: https://devrouw.readthedocs.io/
Author: Aitzaz Imtiaz
Author-email: aitzazimtiaz855@gmail.com
Classifier: Development Status :: 3 - Alpha
Classifier: Programming Language :: Python :: 3
Classifier: License :: OSI Approved :: MIT License
Classifier: Operating System :: OS Independent
Requires-Python: >=3.6
License-File: LICENSE
Requires-Dist: pandas
Requires-Dist: matplotlib
Requires-Dist: scipy
